edfi_google_classroom_extractor/__init__.py
edfi_google_classroom_extractor/__main__.py
edfi_google_classroom_extractor/api/__init__.py
edfi_google_classroom_extractor/api/api_caller.py
edfi_google_classroom_extractor/api/courses.py
edfi_google_classroom_extractor/api/coursework.py
edfi_google_classroom_extractor/api/students.py
edfi_google_classroom_extractor/api/submissions.py
edfi_google_classroom_extractor/api/teachers.py
edfi_google_classroom_extractor/api/usage.py
edfi_google_classroom_extractor/config.py
edfi_google_classroom_extractor/facade.py
edfi_google_classroom_extractor/helpers/__init__.py
edfi_google_classroom_extractor/helpers/arg_parser.py
edfi_google_classroom_extractor/helpers/constants.py
edfi_google_classroom_extractor/mapping/__init__.py
edfi_google_classroom_extractor/mapping/assignment_submissions.py
edfi_google_classroom_extractor/mapping/assignments.py
edfi_google_classroom_extractor/mapping/constants.py
edfi_google_classroom_extractor/mapping/sections.py
edfi_google_classroom_extractor/mapping/user_section_associations.py
edfi_google_classroom_extractor/mapping/user_submission_activities.py
edfi_google_classroom_extractor/mapping/users.py
edfi_google_classroom_extractor-1.2.2.dist-info/METADATA
edfi_google_classroom_extractor-1.2.2.dist-info/WHEEL
edfi_google_classroom_extractor-1.2.2.dist-info/RECORD
