Metadata-Version: 2.1
Name: edfi-google-classroom-extractor
Version: 1.2.2
Summary: Extract tool for retrieving student data from Google Classroom
Home-page: https://docs.ed-fi.org/getting-started/edfi-exchange/technology/ed-fi-lms-toolkit
License: Apache-2.0
Author: Ed-Fi Alliance, LLC, and contributors
Requires-Python: >3.9.1,<4.0.0
Classifier: License :: OSI Approved :: Apache Software License
Classifier: Programming Language :: Python :: 3
Classifier: Programming Language :: Python :: 3.10
Classifier: Programming Language :: Python :: 3.11
Classifier: Programming Language :: Python :: 3.12
Requires-Dist: ConfigArgParse (>=1.2.3,<2.0.0)
Requires-Dist: SQLAlchemy (>=1.3.19,<2.0.0)
Requires-Dist: cryptography (>=44.0.1,<45.0.0)
Requires-Dist: edfi-lms-extractor-lib (>=1.1.6,<2.0.0)
Requires-Dist: edfi-lms-file-utils (>=1.0.6,<2.0.0)
Requires-Dist: errorhandler (>=2.0.1,<3.0.0)
Requires-Dist: google-api-python-client (>=1.11.0,<2.0.0)
Requires-Dist: google-auth-oauthlib (>=0.4.1,<0.5.0)
Requires-Dist: numpy (>=1,<2)
Requires-Dist: opnieuw (>=1.1.0,<2.0.0)
Requires-Dist: pandas (<2.0.0)
Requires-Dist: python-dotenv (>=0.15.0,<0.16.0)
Requires-Dist: tail-recursive (>=2.0.0,<3.0.0)
Requires-Dist: xxhash (>=2.0.0,<3.0.0)
Project-URL: Repository, https://github.com/Ed-Fi-Exchange-OSS/LMS-Toolkit
